CocosBot/__init__.py
CocosBot/browser.py
CocosBot/cocos_capital.py
CocosBot/data_transformations.py
CocosBot/gmail_2fa.py
CocosBot/urls.py
CocosBot/config/__init__.py
CocosBot/config/enums.py
CocosBot/config/general.py
CocosBot/config/selectors.py
CocosBot/config/urls.py
CocosBot/core/__init__.py
CocosBot/core/browser.py
CocosBot/core/cocos_capital.py
CocosBot/services/__init__.py
CocosBot/services/auth.py
CocosBot/services/market.py
CocosBot/services/user.py
CocosBot/utils/__init__.py
CocosBot/utils/data_transformations.py
CocosBot/utils/gmail_2fa.py
CocosBot/utils/validators.py
CocosBot-0.1.0.dist-info/METADATA
CocosBot-0.1.0.dist-info/WHEEL
CocosBot-0.1.0.dist-info/top_level.txt
CocosBot-0.1.0.dist-info/RECORD
