Metadata-Version: 2.1
Name: CocosBot
Version: 0.1.0
Summary: Automation for operations and API data extraction from Cocos Capital broker.
Home-page: https://github.com/PabloAlaniz/CocosBot
Author: Pablo Alaniz
License: MIT
Keywords: cocos bot automation broker api
Classifier: Development Status :: 3 - Alpha
Classifier: Intended Audience :: Developers
Classifier: Topic :: Software Development :: Libraries
Classifier: Programming Language :: Python :: 3.12
Classifier: License :: OSI Approved :: MIT License
Classifier: Operating System :: OS Independent
Requires-Python: >=3.12
Requires-Dist: playwright>=1.0.0
Requires-Dist: beautifulsoup4
